{"propertiesBar":{"properties":[{"name":"Layout","expanded":true,"children":[{"name":"Size","expanded":false,"children":[]}]},{"name":"Effects","expanded":true,"children":[]},{"name":"Editor","expanded":true,"children":[{"name":"Margins","expanded":true,"children":[]},{"name":"Grid size","expanded":false,"children":[]}]}],"scrollPosition":0},"grid":{"show":true,"snap":true,"width":8,"height":8},"marginWidth":8,"marginHeight":8,"showCollisionPolygons":false,"showTranslucentInactiveLayers":false,"tabColor":[0.9999999999999999,0.95,0.8000000000000002,1],"layers":[{"name":"Background","propertiesBar":{"properties":[{"name":"Layer properties","expanded":true,"children":[]},{"name":"Scroll & zoom","expanded":true,"children":[{"name":"Parallax","expanded":false,"children":[]}]},{"name":"Appearance","expanded":true,"children":[]},{"name":"Effects","expanded":true,"children":[]},{"name":"Editor","expanded":true,"children":[]}],"scrollPosition":0},"visibleInEditor":true,"locked":false,"parallaxInEditor":false,"opacity":1,"translucent":false},{"name":"Sprites","propertiesBar":{},"visibleInEditor":true,"locked":false,"parallaxInEditor":false,"opacity":1,"translucent":false},{"name":"HUD","propertiesBar":{},"visibleInEditor":true,"locked":true,"parallaxInEditor":false,"opacity":1,"translucent":false},{"name":"Collisions","propertiesBar":{"properties":[{"name":"Layer properties","expanded":true,"children":[]},{"name":"Scroll & zoom","expanded":true,"children":[{"name":"Parallax","expanded":false,"children":[]}]},{"name":"Appearance","expanded":true,"children":[]},{"name":"Effects","expanded":true,"children":[]},{"name":"Editor","expanded":true,"children":[]}],"scrollPosition":0},"visibleInEditor":false,"locked":true,"parallaxInEditor":false,"opacity":1,"translucent":false},{"name":"Borders","propertiesBar":{},"visibleInEditor":true,"locked":true,"parallaxInEditor":false,"opacity":1,"translucent":false}],"view":{"x":313,"y":96,"z":100,"activeLayer":"Borders"},"selectedInstances":[],"instanceCollections":[{"uids":[4,6,8],"properties":{"properties":[{"name":"Object type properties","expanded":true,"children":[]},{"name":"Common","expanded":true,"children":[{"name":"Position","expanded":false,"children":[]},{"name":"Size","expanded":false,"children":[]}]},{"name":"Effects","expanded":true,"children":[]},{"name":"Properties","expanded":true,"children":[]}],"scrollPosition":0}},{"uids":[22,23,25],"properties":{"properties":[{"name":"Object type properties","expanded":true,"children":[]},{"name":"Common","expanded":true,"children":[{"name":"Position","expanded":false,"children":[]},{"name":"Size","expanded":false,"children":[]}]},{"name":"Instance variables","expanded":true,"children":[]},{"name":"Behaviors","expanded":true,"children":[]},{"name":"Effects","expanded":true,"children":[]},{"name":"Container","expanded":true,"children":[]},{"name":"Properties","expanded":true,"children":[]}],"scrollPosition":0}},{"uids":[1,4,6,8,9,10,11,13,14,15,16,17,18,19,20,22,23,24,26,27,28],"properties":{"properties":[{"name":"Common","expanded":true,"children":[{"name":"Position","expanded":false,"children":[]},{"name":"Size","expanded":false,"children":[]}]},{"name":"Effects","expanded":true,"children":[]}],"scrollPosition":0}},{"uids":[14],"properties":{"properties":[{"name":"Object type properties","expanded":true,"children":[]},{"name":"Common","expanded":true,"children":[{"name":"Position","expanded":false,"children":[]},{"name":"Size","expanded":false,"children":[]}]},{"name":"Instance variables","expanded":true,"children":[]},{"name":"Behaviors","expanded":true,"children":[]},{"name":"Effects","expanded":true,"children":[]},{"name":"Container","expanded":true,"children":[]},{"name":"Properties","expanded":true,"children":[]}],"scrollPosition":0}},{"uids":[8],"properties":{"properties":[{"name":"Object type properties","expanded":true,"children":[]},{"name":"Common","expanded":true,"children":[{"name":"Position","expanded":false,"children":[]},{"name":"Size","expanded":false,"children":[]}]},{"name":"Instance variables","expanded":true,"children":[]},{"name":"Behaviors","expanded":true,"children":[]},{"name":"Effects","expanded":true,"children":[]},{"name":"Container","expanded":true,"children":[]},{"name":"Properties","expanded":true,"children":[]}],"scrollPosition":0}},{"uids":[8],"properties":{"properties":[{"name":"Object type properties","expanded":true,"children":[]},{"name":"Common","expanded":true,"children":[{"name":"Position","expanded":false,"children":[]},{"name":"Size","expanded":false,"children":[]}]},{"name":"Instance variables","expanded":true,"children":[]},{"name":"Behaviors","expanded":true,"children":[]},{"name":"Effects","expanded":true,"children":[]},{"name":"Container","expanded":true,"children":[]},{"name":"Properties","expanded":true,"children":[]}],"scrollPosition":0}},{"uids":[13],"properties":{"properties":[{"name":"Object type properties","expanded":true,"children":[]},{"name":"Common","expanded":true,"children":[{"name":"Position","expanded":false,"children":[]},{"name":"Size","expanded":false,"children":[]}]},{"name":"Instance variables","expanded":true,"children":[]},{"name":"Behaviors","expanded":true,"children":[]},{"name":"Effects","expanded":true,"children":[]},{"name":"Container","expanded":true,"children":[]},{"name":"Properties","expanded":true,"children":[]}],"scrollPosition":0}},{"uids":[11],"properties":{"properties":[{"name":"Object type properties","expanded":true,"children":[]},{"name":"Common","expanded":true,"children":[{"name":"Position","expanded":false,"children":[]},{"name":"Size","expanded":false,"children":[]}]},{"name":"Instance variables","expanded":true,"children":[]},{"name":"Behaviors","expanded":true,"children":[]},{"name":"Effects","expanded":true,"children":[]},{"name":"Container","expanded":true,"children":[]},{"name":"Properties","expanded":true,"children":[]}],"scrollPosition":0}},{"uids":[17],"properties":{"properties":[{"name":"Object type properties","expanded":true,"children":[]},{"name":"Common","expanded":true,"children":[{"name":"Position","expanded":false,"children":[]},{"name":"Size","expanded":false,"children":[]}]},{"name":"Instance variables","expanded":true,"children":[]},{"name":"Behaviors","expanded":true,"children":[]},{"name":"Effects","expanded":true,"children":[]},{"name":"Container","expanded":true,"children":[]},{"name":"Properties","expanded":true,"children":[]}],"scrollPosition":0}},{"uids":[17],"properties":{"properties":[{"name":"Object type properties","expanded":true,"children":[]},{"name":"Common","expanded":true,"children":[{"name":"Position","expanded":false,"children":[]},{"name":"Size","expanded":false,"children":[]}]},{"name":"Instance variables","expanded":true,"children":[]},{"name":"Behaviors","expanded":true,"children":[]},{"name":"Effects","expanded":true,"children":[]},{"name":"Container","expanded":true,"children":[]},{"name":"Properties","expanded":true,"children":[]}],"scrollPosition":0}},{"uids":[17],"properties":{"properties":[{"name":"Object type properties","expanded":true,"children":[]},{"name":"Common","expanded":true,"children":[{"name":"Position","expanded":false,"children":[]},{"name":"Size","expanded":false,"children":[]}]},{"name":"Instance variables","expanded":true,"children":[]},{"name":"Behaviors","expanded":true,"children":[]},{"name":"Effects","expanded":true,"children":[]},{"name":"Container","expanded":true,"children":[]},{"name":"Properties","expanded":true,"children":[]}],"scrollPosition":0}},{"uids":[13],"properties":{"properties":[{"name":"Object type properties","expanded":true,"children":[]},{"name":"Common","expanded":true,"children":[{"name":"Position","expanded":false,"children":[]},{"name":"Size","expanded":false,"children":[]}]},{"name":"Instance variables","expanded":true,"children":[]},{"name":"Behaviors","expanded":true,"children":[]},{"name":"Effects","expanded":true,"children":[]},{"name":"Container","expanded":true,"children":[]},{"name":"Properties","expanded":true,"children":[]}],"scrollPosition":0}},{"uids":[11],"properties":{"properties":[{"name":"Object type properties","expanded":true,"children":[]},{"name":"Common","expanded":true,"children":[{"name":"Position","expanded":false,"children":[]},{"name":"Size","expanded":false,"children":[]}]},{"name":"Instance variables","expanded":true,"children":[]},{"name":"Behaviors","expanded":true,"children":[]},{"name":"Effects","expanded":true,"children":[]},{"name":"Container","expanded":true,"children":[]},{"name":"Properties","expanded":true,"children":[]}],"scrollPosition":0}},{"uids":[8],"properties":{"properties":[{"name":"Object type properties","expanded":true,"children":[]},{"name":"Common","expanded":true,"children":[{"name":"Position","expanded":false,"children":[]},{"name":"Size","expanded":false,"children":[]}]},{"name":"Instance variables","expanded":true,"children":[]},{"name":"Behaviors","expanded":true,"children":[]},{"name":"Effects","expanded":true,"children":[]},{"name":"Container","expanded":true,"children":[]},{"name":"Properties","expanded":true,"children":[]}],"scrollPosition":0}},{"uids":[27],"properties":{"properties":[{"name":"Object type properties","expanded":true,"children":[]},{"name":"Common","expanded":true,"children":[{"name":"Position","expanded":false,"children":[]},{"name":"Size","expanded":false,"children":[]}]},{"name":"Instance variables","expanded":true,"children":[]},{"name":"Behaviors","expanded":true,"children":[]},{"name":"Effects","expanded":true,"children":[]},{"name":"Container","expanded":true,"children":[]},{"name":"Properties","expanded":true,"children":[]}],"scrollPosition":0}},{"uids":[28],"properties":{"properties":[{"name":"Object type properties","expanded":true,"children":[]},{"name":"Common","expanded":true,"children":[{"name":"Position","expanded":false,"children":[]},{"name":"Size","expanded":false,"children":[]}]},{"name":"Instance variables","expanded":true,"children":[]},{"name":"Behaviors","expanded":true,"children":[]},{"name":"Effects","expanded":true,"children":[]},{"name":"Container","expanded":true,"children":[]},{"name":"Properties","expanded":true,"children":[]}],"scrollPosition":0}},{"uids":[22],"properties":{"properties":[{"name":"Object type properties","expanded":true,"children":[]},{"name":"Common","expanded":true,"children":[{"name":"Position","expanded":false,"children":[]},{"name":"Size","expanded":false,"children":[]}]},{"name":"Instance variables","expanded":true,"children":[]},{"name":"Behaviors","expanded":true,"children":[]},{"name":"Effects","expanded":true,"children":[]},{"name":"Container","expanded":true,"children":[]},{"name":"Properties","expanded":true,"children":[]}],"scrollPosition":0}},{"uids":[23],"properties":{"properties":[{"name":"Object type properties","expanded":true,"children":[]},{"name":"Common","expanded":true,"children":[{"name":"Position","expanded":false,"children":[]},{"name":"Size","expanded":false,"children":[]}]},{"name":"Instance variables","expanded":true,"children":[]},{"name":"Behaviors","expanded":true,"children":[]},{"name":"Effects","expanded":true,"children":[]},{"name":"Container","expanded":true,"children":[]},{"name":"Properties","expanded":true,"children":[]}],"scrollPosition":0}},{"uids":[26],"properties":{"properties":[{"name":"Object type properties","expanded":true,"children":[]},{"name":"Common","expanded":true,"children":[{"name":"Position","expanded":false,"children":[]},{"name":"Size","expanded":false,"children":[]}]},{"name":"Instance variables","expanded":true,"children":[]},{"name":"Behaviors","expanded":true,"children":[{"name":"ScrollTo","expanded":true,"children":[]}]},{"name":"Effects","expanded":true,"children":[]},{"name":"Container","expanded":true,"children":[]},{"name":"Properties","expanded":true,"children":[]}],"scrollPosition":0}},{"uids":[10],"properties":{"properties":[{"name":"Object type properties","expanded":true,"children":[]},{"name":"Common","expanded":true,"children":[{"name":"Position","expanded":false,"children":[]},{"name":"Size","expanded":false,"children":[]}]},{"name":"Instance variables","expanded":true,"children":[]},{"name":"Behaviors","expanded":true,"children":[]},{"name":"Effects","expanded":true,"children":[]},{"name":"Container","expanded":true,"children":[]},{"name":"Properties","expanded":true,"children":[]}],"scrollPosition":0}},{"uids":[10],"properties":{"properties":[{"name":"Object type properties","expanded":true,"children":[]},{"name":"Common","expanded":true,"children":[{"name":"Position","expanded":false,"children":[]},{"name":"Size","expanded":false,"children":[]}]},{"name":"Instance variables","expanded":true,"children":[]},{"name":"Behaviors","expanded":true,"children":[]},{"name":"Effects","expanded":true,"children":[]},{"name":"Container","expanded":true,"children":[]},{"name":"Properties","expanded":true,"children":[]}],"scrollPosition":0}},{"uids":[1],"properties":{"properties":[{"name":"Object type properties","expanded":true,"children":[]},{"name":"Common","expanded":true,"children":[{"name":"Position","expanded":false,"children":[]},{"name":"Size","expanded":false,"children":[]}]},{"name":"Instance variables","expanded":true,"children":[]},{"name":"Behaviors","expanded":true,"children":[]},{"name":"Effects","expanded":true,"children":[]},{"name":"Container","expanded":true,"children":[]},{"name":"Properties","expanded":true,"children":[]}],"scrollPosition":0}},{"uids":[9],"properties":{"properties":[{"name":"Object type properties","expanded":true,"children":[]},{"name":"Common","expanded":true,"children":[{"name":"Position","expanded":false,"children":[]},{"name":"Size","expanded":false,"children":[]}]},{"name":"Instance variables","expanded":true,"children":[]},{"name":"Behaviors","expanded":true,"children":[]},{"name":"Effects","expanded":true,"children":[]},{"name":"Container","expanded":true,"children":[]},{"name":"Properties","expanded":true,"children":[]}],"scrollPosition":0}},{"uids":[9],"properties":{"properties":[{"name":"Object type properties","expanded":true,"children":[]},{"name":"Common","expanded":true,"children":[{"name":"Position","expanded":false,"children":[]},{"name":"Size","expanded":false,"children":[]}]},{"name":"Instance variables","expanded":true,"children":[]},{"name":"Behaviors","expanded":true,"children":[]},{"name":"Effects","expanded":true,"children":[]},{"name":"Container","expanded":true,"children":[]},{"name":"Properties","expanded":true,"children":[]}],"scrollPosition":0}},{"uids":[19],"properties":{"properties":[{"name":"Object type properties","expanded":true,"children":[]},{"name":"Common","expanded":true,"children":[{"name":"Position","expanded":false,"children":[]},{"name":"Size","expanded":false,"children":[]}]},{"name":"Instance variables","expanded":true,"children":[]},{"name":"Behaviors","expanded":true,"children":[]},{"name":"Effects","expanded":true,"children":[]},{"name":"Container","expanded":true,"children":[]},{"name":"Properties","expanded":true,"children":[]}],"scrollPosition":0}},{"uids":[16],"properties":{"properties":[{"name":"Object type properties","expanded":true,"children":[]},{"name":"Common","expanded":true,"children":[{"name":"Position","expanded":false,"children":[]},{"name":"Size","expanded":false,"children":[]}]},{"name":"Instance variables","expanded":true,"children":[]},{"name":"Behaviors","expanded":true,"children":[]},{"name":"Effects","expanded":true,"children":[]},{"name":"Container","expanded":true,"children":[]},{"name":"Properties","expanded":true,"children":[]}],"scrollPosition":0}},{"uids":[13],"properties":{"properties":[{"name":"Object type properties","expanded":true,"children":[]},{"name":"Common","expanded":true,"children":[{"name":"Position","expanded":false,"children":[]},{"name":"Size","expanded":false,"children":[]}]},{"name":"Instance variables","expanded":true,"children":[]},{"name":"Behaviors","expanded":true,"children":[]},{"name":"Effects","expanded":true,"children":[]},{"name":"Container","expanded":true,"children":[]},{"name":"Properties","expanded":true,"children":[]}],"scrollPosition":0}},{"uids":[20],"properties":{"properties":[{"name":"Object type properties","expanded":true,"children":[]},{"name":"Common","expanded":true,"children":[{"name":"Position","expanded":false,"children":[]},{"name":"Size","expanded":false,"children":[]}]},{"name":"Instance variables","expanded":true,"children":[]},{"name":"Behaviors","expanded":true,"children":[]},{"name":"Effects","expanded":true,"children":[]},{"name":"Container","expanded":true,"children":[]},{"name":"Properties","expanded":true,"children":[]}],"scrollPosition":0}},{"uids":[4,8],"properties":{"properties":[{"name":"Object type properties","expanded":true,"children":[]},{"name":"Common","expanded":true,"children":[{"name":"Position","expanded":false,"children":[]},{"name":"Size","expanded":false,"children":[]}]},{"name":"Effects","expanded":true,"children":[]},{"name":"Properties","expanded":true,"children":[]}],"scrollPosition":0}},{"uids":[13,14],"properties":{"properties":[{"name":"Object type properties","expanded":true,"children":[]},{"name":"Common","expanded":true,"children":[{"name":"Position","expanded":false,"children":[]},{"name":"Size","expanded":false,"children":[]}]},{"name":"Instance variables","expanded":true,"children":[]},{"name":"Behaviors","expanded":true,"children":[]},{"name":"Effects","expanded":true,"children":[]},{"name":"Container","expanded":true,"children":[]},{"name":"Properties","expanded":true,"children":[]}],"scrollPosition":0}},{"uids":[10,11],"properties":{"properties":[{"name":"Object type properties","expanded":true,"children":[]},{"name":"Common","expanded":true,"children":[{"name":"Position","expanded":false,"children":[]},{"name":"Size","expanded":false,"children":[]}]},{"name":"Instance variables","expanded":true,"children":[]},{"name":"Behaviors","expanded":true,"children":[]},{"name":"Effects","expanded":true,"children":[]},{"name":"Container","expanded":true,"children":[]},{"name":"Properties","expanded":true,"children":[]}],"scrollPosition":0}},{"uids":[11,17],"properties":{"properties":[{"name":"Object type properties","expanded":true,"children":[]},{"name":"Common","expanded":true,"children":[{"name":"Position","expanded":false,"children":[]},{"name":"Size","expanded":false,"children":[]}]},{"name":"Instance variables","expanded":true,"children":[]},{"name":"Behaviors","expanded":true,"children":[]},{"name":"Effects","expanded":true,"children":[]},{"name":"Container","expanded":true,"children":[]},{"name":"Properties","expanded":true,"children":[]}],"scrollPosition":0}},{"uids":[8],"properties":{"properties":[{"name":"Object type properties","expanded":true,"children":[]},{"name":"Common","expanded":true,"children":[{"name":"Position","expanded":false,"children":[]},{"name":"Size","expanded":false,"children":[]}]},{"name":"Instance variables","expanded":true,"children":[]},{"name":"Behaviors","expanded":true,"children":[]},{"name":"Effects","expanded":true,"children":[]},{"name":"Container","expanded":true,"children":[]},{"name":"Properties","expanded":true,"children":[]}],"scrollPosition":0}},{"uids":[14],"properties":{"properties":[{"name":"Object type properties","expanded":true,"children":[]},{"name":"Common","expanded":true,"children":[{"name":"Position","expanded":false,"children":[]},{"name":"Size","expanded":false,"children":[]}]},{"name":"Instance variables","expanded":true,"children":[]},{"name":"Behaviors","expanded":true,"children":[]},{"name":"Effects","expanded":true,"children":[]},{"name":"Container","expanded":true,"children":[]},{"name":"Properties","expanded":true,"children":[]}],"scrollPosition":0}},{"uids":[10],"properties":{"properties":[{"name":"Object type properties","expanded":true,"children":[]},{"name":"Common","expanded":true,"children":[{"name":"Position","expanded":false,"children":[]},{"name":"Size","expanded":false,"children":[]}]},{"name":"Instance variables","expanded":true,"children":[]},{"name":"Behaviors","expanded":true,"children":[]},{"name":"Effects","expanded":true,"children":[]},{"name":"Container","expanded":true,"children":[]},{"name":"Properties","expanded":true,"children":[]}],"scrollPosition":0}},{"uids":[18],"properties":{"properties":[{"name":"Object type properties","expanded":true,"children":[]},{"name":"Common","expanded":true,"children":[{"name":"Position","expanded":false,"children":[]},{"name":"Size","expanded":false,"children":[]}]},{"name":"Instance variables","expanded":true,"children":[]},{"name":"Behaviors","expanded":true,"children":[]},{"name":"Effects","expanded":true,"children":[]},{"name":"Container","expanded":true,"children":[]},{"name":"Properties","expanded":true,"children":[]}],"scrollPosition":0}},{"uids":[6],"properties":{"properties":[{"name":"Object type properties","expanded":true,"children":[]},{"name":"Common","expanded":true,"children":[{"name":"Position","expanded":false,"children":[]},{"name":"Size","expanded":false,"children":[]}]},{"name":"Instance variables","expanded":true,"children":[]},{"name":"Behaviors","expanded":true,"children":[]},{"name":"Effects","expanded":true,"children":[]},{"name":"Container","expanded":true,"children":[]},{"name":"Properties","expanded":true,"children":[]}],"scrollPosition":0}},{"uids":[4],"properties":{"properties":[{"name":"Object type properties","expanded":true,"children":[]},{"name":"Common","expanded":true,"children":[{"name":"Position","expanded":false,"children":[]},{"name":"Size","expanded":false,"children":[]}]},{"name":"Instance variables","expanded":true,"children":[]},{"name":"Behaviors","expanded":true,"children":[]},{"name":"Effects","expanded":true,"children":[]},{"name":"Container","expanded":true,"children":[]},{"name":"Properties","expanded":true,"children":[]}],"scrollPosition":0}},{"uids":[6],"properties":{"properties":[{"name":"Object type properties","expanded":true,"children":[]},{"name":"Common","expanded":true,"children":[{"name":"Position","expanded":false,"children":[]},{"name":"Size","expanded":false,"children":[]}]},{"name":"Instance variables","expanded":true,"children":[]},{"name":"Behaviors","expanded":true,"children":[]},{"name":"Effects","expanded":true,"children":[]},{"name":"Container","expanded":true,"children":[]},{"name":"Properties","expanded":true,"children":[]}],"scrollPosition":0}},{"uids":[15],"properties":{"properties":[{"name":"Object type properties","expanded":true,"children":[]},{"name":"Common","expanded":true,"children":[{"name":"Position","expanded":false,"children":[]},{"name":"Size","expanded":false,"children":[]}]},{"name":"Instance variables","expanded":true,"children":[]},{"name":"Behaviors","expanded":true,"children":[]},{"name":"Effects","expanded":true,"children":[]},{"name":"Container","expanded":true,"children":[]},{"name":"Properties","expanded":true,"children":[]}],"scrollPosition":0}},{"uids":[25],"properties":{"properties":[{"name":"Object type properties","expanded":true,"children":[]},{"name":"Common","expanded":true,"children":[{"name":"Position","expanded":false,"children":[]},{"name":"Size","expanded":false,"children":[]}]},{"name":"Instance variables","expanded":true,"children":[]},{"name":"Behaviors","expanded":true,"children":[]},{"name":"Effects","expanded":true,"children":[]},{"name":"Container","expanded":true,"children":[]},{"name":"Properties","expanded":true,"children":[]}],"scrollPosition":0}},{"uids":[12],"properties":{"properties":[{"name":"Object type properties","expanded":true,"children":[]},{"name":"Common","expanded":true,"children":[{"name":"Position","expanded":false,"children":[]},{"name":"Size","expanded":false,"children":[]}]},{"name":"Instance variables","expanded":true,"children":[]},{"name":"Behaviors","expanded":true,"children":[]},{"name":"Effects","expanded":true,"children":[]},{"name":"Container","expanded":true,"children":[]},{"name":"Properties","expanded":true,"children":[]}],"scrollPosition":0}},{"uids":[12],"properties":{"properties":[{"name":"Object type properties","expanded":true,"children":[]},{"name":"Common","expanded":true,"children":[{"name":"Position","expanded":false,"children":[]},{"name":"Size","expanded":false,"children":[]}]},{"name":"Instance variables","expanded":true,"children":[]},{"name":"Behaviors","expanded":true,"children":[]},{"name":"Effects","expanded":true,"children":[]},{"name":"Container","expanded":true,"children":[]},{"name":"Properties","expanded":true,"children":[]}],"scrollPosition":0}},{"uids":[24],"properties":{"properties":[{"name":"Object type properties","expanded":true,"children":[]},{"name":"Common","expanded":true,"children":[{"name":"Position","expanded":false,"children":[]},{"name":"Size","expanded":false,"children":[]}]},{"name":"Instance variables","expanded":true,"children":[]},{"name":"Behaviors","expanded":true,"children":[]},{"name":"Effects","expanded":true,"children":[]},{"name":"Container","expanded":true,"children":[]},{"name":"Properties","expanded":true,"children":[]}],"scrollPosition":0}}]}